pyaddict/__init__.py
pyaddict/py.typed
pyaddict/pyaddict.py
pyaddict/interfaces/__init__.py
pyaddict/interfaces/common.py
pyaddict/schema/__init__.py
pyaddict/schema/base.py
pyaddict/schema/result.py
pyaddict/schema/schema.py
pyaddict/types/__init__.py
pyaddict/types/types.py
pyaddict-1.2.2.dist-info/METADATA
pyaddict-1.2.2.dist-info/WHEEL
pyaddict-1.2.2.dist-info/licenses/LICENSE
pyaddict-1.2.2.dist-info/RECORD
