Metadata-Version: 2.4
Name: pyaddict
Version: 1.2.2
Summary: yet another dict library
Project-URL: Homepage, https://github.com/dxstiny/pyaddict
Project-URL: Bug Tracker, https://github.com/dxstiny/pyaddict/issues
Author-email: dxstiny <dxstiny.gh@gmail.com>
License: Mozilla Public License Version 2.0
License-File: LICENSE
Classifier: License :: OSI Approved :: MIT License
Classifier: Operating System :: OS Independent
Classifier: Programming Language :: Python :: 3
Requires-Python: >=3.9
